setup.py
binomial_gaussian_probability_CL/Binomialdistribution.py
binomial_gaussian_probability_CL/Gaussiandistribution.py
binomial_gaussian_probability_CL/Generaldistribution.py
binomial_gaussian_probability_CL/__init__.py
binomial_gaussian_probability_CL.egg-info/PKG-INFO
binomial_gaussian_probability_CL.egg-info/SOURCES.txt
binomial_gaussian_probability_CL.egg-info/dependency_links.txt
binomial_gaussian_probability_CL.egg-info/not-zip-safe
binomial_gaussian_probability_CL.egg-info/top_level.txt