Metadata-Version: 1.0
Name: binomial-gaussian-probability-CL
Version: 1.0
Summary: Binomial and Gaussian distributions
Home-page: UNKNOWN
Author: Charline LI
Author-email: lch129444@hotmail.com
License: UNKNOWN
Platform: UNKNOWN
